{
	"operation":
		[
			{
				"id":1,
				"OperName":"地面1X",
				"roleID":1,
				"skillid":11101,
				"skillType":0,
				"leafid":[ 2, 18, 11, 20, 21 ],
				"mainkey":{ "key" : 3,"mode" : 1},
				"subkey":{ "key" : 1,"mode" : 1},
				"isboot":1,
				"sstate":1,
				"parmsecmin":1000,
				"parmsecmax":1000
			},
			{
				"id":2,
				"OperName":"地面2X",
				"roleID":1,
				"skillid":11102,
				"skillType":0,
				"leafid":[ 3, 18, 12, 20, 21 ],
				"mainkey":{ "key" : 3,"mode" : 1},
				"subkey":{ "key" : 1,"mode" : 1},
				"isboot":0,
				"sstate":1,
				"parmsecmin":0,
				"parmsecmax":10000
			},
			{
				"id":3,
				"OperName":"地面3X",
				"roleID":1,
				"skillid":11103,
				"skillType":0,
				"leafid":[ 4, 18, 13, 20, 21 ],
				"mainkey":{ "key" : 3,"mode" : 1},
				"subkey":{ "key" : 1,"mode" : 1},
				"isboot":0,
				"sstate":1,
				"parmsecmin":0,
				"parmsecmax":10000
			},
			{
				"id":4,
				"OperName":"地面4X",
				"roleID":1,
				"skillid":11104,
				"skillType":0,
				"leafid":[ 5, 18, 14, 20, 21 ],
				"mainkey":{ "key" : 3,"mode" : 1},
				"subkey":{ "key" : 1,"mode" : 1},
				"isboot":0,
				"sstate":1,
				"parmsecmin":0,
				"parmsecmax":10000
			},
			{
				"id":5,
				"OperName":"地面5X",
				"roleID":1,
				"skillid":11105,
				"skillType":0,
				"leafid":[ 15, 20, 21 ],
				"mainkey":{ "key" : 3,"mode" : 1},
				"subkey":{ "key" : 1,"mode" : 1},
				"isboot":0,
				"sstate":1,
				"parmsecmin":0,
				"parmsecmax":10000
			},
			{
				"id":6,
				"OperName":"空中1X",
				"roleID":1,
				"skillid":11106,
				"skillType":0,
				"leafid":[ 7, 19, 17, 22 ],
				"mainkey":{ "key" : 3,"mode" : 1},
				"subkey":{ "key" : 1,"mode" : 1},
				"isboot":1,
				"sstate":2,
				"parmsecmin":0,
				"parmsecmax":10000
			},
			{
				"id":7,
				"OperName":"空中2X",
				"roleID":1,
				"skillid":11107,
				"skillType":0,
				"leafid":[ 8, 19, 17, 22 ],
				"mainkey":{ "key" : 3,"mode" : 1},
				"subkey":{ "key" : 1,"mode" : 1},
				"isboot":0,
				"sstate":2,
				"parmsecmin":0,
				"parmsecmax":10000
			},
			{
				"id":8,
				"OperName":"空中3X",
				"roleID":1,
				"skillid":11108,
				"skillType":0,
				"leafid":[ 9, 19, 17, 22 ],
				"mainkey":{ "key" : 3,"mode" : 1},
				"subkey":{ "key" : 1,"mode" : 1},
				"isboot":0,
				"sstate":2,
				"parmsecmin":0,
				"parmsecmax":10000
			},
			{
				"id":9,
				"OperName":"空中4X",
				"roleID":1,
				"skillid":11109,
				"skillType":0,
				"leafid":[ 10, 19, 17, 22 ],
				"mainkey":{ "key" : 3,"mode" : 1},
				"subkey":{ "key" : 1,"mode" : 1},
				"isboot":0,
				"sstate":2,
				"parmsecmin":0,
				"parmsecmax":10000
			},
			{
				"id":10,
				"OperName":"空中5X",
				"roleID":1,
				"skillid":11110,
				"skillType":0,
				"leafid":[],
				"mainkey":{ "key" : 3,"mode" : 1},
				"subkey":{ "key" : 1,"mode" : 1},
				"isboot":0,
				"sstate":2,
				"parmsecmin":0,
				"parmsecmax":10000
			},
			{
				"id":11,
				"OperName":"Y连招1",
				"roleID":1,
				"skillid":11203,
				"skillType":0,
				"leafid":[],
				"mainkey":{ "key" : 4,"mode" : 1},
				"subkey":{ "key" : 1,"mode" : 1},
				"isboot":0,
				"sstate":1,
				"parmsecmin":0,
				"parmsecmax":10000
			},
			{
				"id":12,
				"OperName":"Y连招2",
				"roleID":1,
				"skillid":11204,
				"skillType":0,
				"leafid":[],
				"mainkey":{ "key" : 4,"mode" : 1},
				"subkey":{ "key" : 1,"mode" : 1},
				"isboot":0,
				"sstate":1,
				"parmsecmin":0,
				"parmsecmax":10000
			},
			{
				"id":13,
				"OperName":"Y连招3",
				"roleID":1,
				"skillid":11205,
				"skillType":0,
				"leafid":[],
				"mainkey":{ "key" : 4,"mode" : 1},
				"subkey":{ "key" : 1,"mode" : 1},
				"isboot":0,
				"sstate":1,
				"parmsecmin":0,
				"parmsecmax":10000
			},
			{
				"id":14,
				"OperName":"Y连招4",
				"roleID":1,
				"skillid":11206,
				"skillType":0,
				"leafid":[],
				"mainkey":{ "key" : 4,"mode" : 1},
				"subkey":{ "key" : 1,"mode" : 1},
				"isboot":0,
				"sstate":1,
				"parmsecmin":0,
				"parmsecmax":10000
			},
			{
				"id":15,
				"OperName":"Y连招5",
				"roleID":1,
				"skillid":11207,
				"skillType":0,
				"leafid":[],
				"mainkey":{ "key" : 4,"mode" : 1},
				"subkey":{ "key" : 1,"mode" : 1},
				"isboot":0,
				"sstate":1,
				"parmsecmin":0,
				"parmsecmax":10000
			},
			{
				"id":16,
				"OperName":"地面Y",
				"roleID":1,
				"skillid":11201,
				"skillType":0,
				"leafid":[],
				"mainkey":{ "key" : 4,"mode" : 1},
				"subkey":{ "key" : 1,"mode" : 1},
				"isboot":1,
				"sstate":1,
				"parmsecmin":0,
				"parmsecmax":10000
			},
			{
				"id":17,
				"OperName":"空中Y",
				"roleID":1,
				"skillid":11202,
				"skillType":0,
				"leafid":[],
				"mainkey":{ "key" : 4,"mode" : 1},
				"subkey":{ "key" : 1,"mode" : 1},
				"isboot":1,
				"sstate":2,
				"parmsecmin":0,
				"parmsecmax":10000
			},
			{
				"id":18,
				"OperName":"1段上挑",
				"roleID":1,
				"skillid":11301,
				"skillType":0,
				"leafid":[ 6, 17 ],
				"mainkey":{ "key" : 1,"mode" : 1},
				"subkey":{ "key" : 1,"mode" : 1},
				"isboot":0,
				"sstate":1,
				"parmsecmin":0,
				"parmsecmax":10000
			},
			{
				"id":19,
				"OperName":"2段上挑",
				"roleID":1,
				"skillid":11302,
				"skillType":0,
				"leafid":[ 6, 17 ],
				"mainkey":{ "key" : 1,"mode" : 1},
				"subkey":{ "key" : 1,"mode" : 1},
				"isboot":0,
				"sstate":2,
				"parmsecmin":0,
				"parmsecmax":10000
			},
			{
				"id":20,
				"OperName":"格挡",
				"roleID":1,
				"skillid":31402,
				"skillType":1,
				"leafid":[],
				"mainkey":{ "key" : 2,"mode" : 3},
				"subkey":{ "key" : 1,"mode" : 1},
				"isboot":1,
				"sstate":1,
				"parmsecmin":0,
				"parmsecmax":10000
			},
			{
				"id":21,
				"OperName":"闪避",
				"roleID":1,
				"skillid":31401,
				"skillType":1,
				"leafid":[],
				"mainkey":{ "key" : 2,"mode" : 1},
				"subkey":{ "key" : 1,"mode" : 1},
				"isboot":1,
				"sstate":1,
				"parmsecmin":0,
				"parmsecmax":10000
			},
			{
				"id":22,
				"OperName":"受身",
				"roleID":1,
				"skillid":31404,
				"skillType":1,
				"leafid":[],
				"mainkey":{ "key" : 2,"mode" : 4},
				"subkey":{ "key" : 1,"mode" : 1},
				"isboot":1,
				"sstate":0,
				"parmsecmin":0,
				"parmsecmax":10000
			},
			{
				"id":23,
				"OperName":"空中冲刺",
				"roleID":1,
				"skillid":31403,
				"skillType":1,
				"leafid":[ 6, 17 ],
				"mainkey":{ "key" : 2,"mode" : 1},
				"subkey":{ "key" : 1,"mode" : 1},
				"isboot":1,
				"sstate":2,
				"parmsecmin":0,
				"parmsecmax":10000
			},
			{
				"id":24,
				"OperName":"跳跃",
				"roleID":1,
				"skillid":31301,
				"skillType":1,
				"leafid":[],
				"mainkey":{ "key" : 1,"mode" : 1},
				"subkey":{ "key" : 1,"mode" : 1},
				"isboot":1,
				"sstate":1,
				"parmsecmin":0,
				"parmsecmax":10000
			},
			{
				"id":25,
				"OperName":"2段跳跃",
				"roleID":1,
				"skillid":31302,
				"skillType":1,
				"leafid":[],
				"mainkey":{ "key" : 1,"mode" : 1},
				"subkey":{ "key" : 1,"mode" : 1},
				"isboot":1,
				"sstate":2,
				"parmsecmin":0,
				"parmsecmax":10000
			},
			{
				"id":26,
				"OperName":"技能1",
				"roleID":1,
				"skillid":21501,
				"skillType":0,
				"leafid":[],
				"mainkey":{ "key" : 5,"mode" : 1},
				"subkey":{ "key" : 1,"mode" : 1},
				"isboot":1,
				"sstate":1,
				"parmsecmin":0,
				"parmsecmax":10000
			},
			{
				"id":27,
				"OperName":"技能2",
				"roleID":1,
				"skillid":21601,
				"skillType":0,
				"leafid":[],
				"mainkey":{ "key" : 6,"mode" : 1},
				"subkey":{ "key" : 1,"mode" : 1},
				"isboot":1,
				"sstate":1,
				"parmsecmin":0,
				"parmsecmax":10000
			},
			{
				"id":28,
				"OperName":"技能3",
				"roleID":1,
				"skillid":21701,
				"skillType":0,
				"leafid":[],
				"mainkey":{ "key" : 7,"mode" : 1},
				"subkey":{ "key" : 1,"mode" : 1},
				"isboot":1,
				"sstate":1,
				"parmsecmin":0,
				"parmsecmax":10000
			},
			{
				"id":29,
				"OperName":"技能4",
				"roleID":1,
				"skillid":21801,
				"skillType":0,
				"leafid":[],
				"mainkey":{ "key" : 8,"mode" : 1},
				"subkey":{ "key" : 1,"mode" : 1},
				"isboot":1,
				"sstate":1,
				"parmsecmin":0,
				"parmsecmax":10000
			},
			{
				"id":1,
				"OperName":"地面1X",
				"roleID":2,
				"skillid":12101,
				"skillType":0,
				"leafid":[ 2, 18, 11, 20, 21 ],
				"mainkey":{ "key" : 3,"mode" : 1},
				"subkey":{ "key" : 1,"mode" : 1},
				"isboot":1,
				"sstate":1,
				"parmsecmin":1000,
				"parmsecmax":1000
			},
			{
				"id":2,
				"OperName":"地面2X",
				"roleID":2,
				"skillid":12102,
				"skillType":0,
				"leafid":[ 3, 18, 12, 20, 21 ],
				"mainkey":{ "key" : 3,"mode" : 1},
				"subkey":{ "key" : 1,"mode" : 1},
				"isboot":0,
				"sstate":1,
				"parmsecmin":0,
				"parmsecmax":10000
			},
			{
				"id":3,
				"OperName":"地面3X",
				"roleID":2,
				"skillid":12103,
				"skillType":0,
				"leafid":[ 4, 18, 13, 20, 21 ],
				"mainkey":{ "key" : 3,"mode" : 1},
				"subkey":{ "key" : 1,"mode" : 1},
				"isboot":0,
				"sstate":1,
				"parmsecmin":0,
				"parmsecmax":10000
			},
			{
				"id":4,
				"OperName":"地面4X",
				"roleID":2,
				"skillid":12104,
				"skillType":0,
				"leafid":[ 5, 18, 14, 20, 21 ],
				"mainkey":{ "key" : 3,"mode" : 1},
				"subkey":{ "key" : 1,"mode" : 1},
				"isboot":0,
				"sstate":1,
				"parmsecmin":0,
				"parmsecmax":10000
			},
			{
				"id":5,
				"OperName":"地面5X",
				"roleID":2,
				"skillid":12105,
				"skillType":0,
				"leafid":[ 15, 20, 21 ],
				"mainkey":{ "key" : 3,"mode" : 1},
				"subkey":{ "key" : 1,"mode" : 1},
				"isboot":0,
				"sstate":1,
				"parmsecmin":0,
				"parmsecmax":10000
			},
			{
				"id":6,
				"OperName":"空中1X",
				"roleID":2,
				"skillid":12106,
				"skillType":0,
				"leafid":[ 7, 19, 17, 22 ],
				"mainkey":{ "key" : 3,"mode" : 1},
				"subkey":{ "key" : 1,"mode" : 1},
				"isboot":1,
				"sstate":2,
				"parmsecmin":0,
				"parmsecmax":10000
			},
			{
				"id":7,
				"OperName":"空中2X",
				"roleID":2,
				"skillid":12107,
				"skillType":0,
				"leafid":[ 8, 19, 17, 22 ],
				"mainkey":{ "key" : 3,"mode" : 1},
				"subkey":{ "key" : 1,"mode" : 1},
				"isboot":0,
				"sstate":2,
				"parmsecmin":0,
				"parmsecmax":10000
			},
			{
				"id":8,
				"OperName":"空中3X",
				"roleID":2,
				"skillid":12108,
				"skillType":0,
				"leafid":[ 9, 19, 17, 22 ],
				"mainkey":{ "key" : 3,"mode" : 1},
				"subkey":{ "key" : 1,"mode" : 1},
				"isboot":0,
				"sstate":2,
				"parmsecmin":0,
				"parmsecmax":10000
			},
			{
				"id":9,
				"OperName":"空中4X",
				"roleID":2,
				"skillid":12109,
				"skillType":0,
				"leafid":[ 10, 19, 17, 22 ],
				"mainkey":{ "key" : 3,"mode" : 1},
				"subkey":{ "key" : 1,"mode" : 1},
				"isboot":0,
				"sstate":2,
				"parmsecmin":0,
				"parmsecmax":10000
			},
			{
				"id":10,
				"OperName":"空中5X",
				"roleID":2,
				"skillid":12110,
				"skillType":0,
				"leafid":[],
				"mainkey":{ "key" : 3,"mode" : 1},
				"subkey":{ "key" : 1,"mode" : 1},
				"isboot":0,
				"sstate":2,
				"parmsecmin":0,
				"parmsecmax":10000
			},
			{
				"id":11,
				"OperName":"Y连招1",
				"roleID":2,
				"skillid":12203,
				"skillType":0,
				"leafid":[],
				"mainkey":{ "key" : 4,"mode" : 1},
				"subkey":{ "key" : 1,"mode" : 1},
				"isboot":0,
				"sstate":1,
				"parmsecmin":0,
				"parmsecmax":10000
			},
			{
				"id":12,
				"OperName":"Y连招2",
				"roleID":2,
				"skillid":12204,
				"skillType":0,
				"leafid":[],
				"mainkey":{ "key" : 4,"mode" : 1},
				"subkey":{ "key" : 1,"mode" : 1},
				"isboot":0,
				"sstate":1,
				"parmsecmin":0,
				"parmsecmax":10000
			},
			{
				"id":13,
				"OperName":"Y连招3",
				"roleID":2,
				"skillid":12205,
				"skillType":0,
				"leafid":[],
				"mainkey":{ "key" : 4,"mode" : 1},
				"subkey":{ "key" : 1,"mode" : 1},
				"isboot":0,
				"sstate":1,
				"parmsecmin":0,
				"parmsecmax":10000
			},
			{
				"id":14,
				"OperName":"Y连招4",
				"roleID":2,
				"skillid":12206,
				"skillType":0,
				"leafid":[],
				"mainkey":{ "key" : 4,"mode" : 1},
				"subkey":{ "key" : 1,"mode" : 1},
				"isboot":0,
				"sstate":1,
				"parmsecmin":0,
				"parmsecmax":10000
			},
			{
				"id":15,
				"OperName":"Y连招5",
				"roleID":2,
				"skillid":12207,
				"skillType":0,
				"leafid":[],
				"mainkey":{ "key" : 4,"mode" : 1},
				"subkey":{ "key" : 1,"mode" : 1},
				"isboot":0,
				"sstate":1,
				"parmsecmin":0,
				"parmsecmax":10000
			},
			{
				"id":16,
				"OperName":"地面Y",
				"roleID":2,
				"skillid":12201,
				"skillType":0,
				"leafid":[],
				"mainkey":{ "key" : 4,"mode" : 1},
				"subkey":{ "key" : 1,"mode" : 1},
				"isboot":1,
				"sstate":1,
				"parmsecmin":0,
				"parmsecmax":10000
			},
			{
				"id":17,
				"OperName":"空中Y",
				"roleID":2,
				"skillid":12202,
				"skillType":0,
				"leafid":[],
				"mainkey":{ "key" : 4,"mode" : 1},
				"subkey":{ "key" : 1,"mode" : 1},
				"isboot":1,
				"sstate":2,
				"parmsecmin":0,
				"parmsecmax":10000
			},
			{
				"id":18,
				"OperName":"1段上挑",
				"roleID":2,
				"skillid":12301,
				"skillType":0,
				"leafid":[ 6, 17 ],
				"mainkey":{ "key" : 1,"mode" : 1},
				"subkey":{ "key" : 1,"mode" : 1},
				"isboot":0,
				"sstate":1,
				"parmsecmin":0,
				"parmsecmax":10000
			},
			{
				"id":19,
				"OperName":"2段上挑",
				"roleID":2,
				"skillid":12302,
				"skillType":0,
				"leafid":[ 6, 17 ],
				"mainkey":{ "key" : 1,"mode" : 1},
				"subkey":{ "key" : 1,"mode" : 1},
				"isboot":0,
				"sstate":2,
				"parmsecmin":0,
				"parmsecmax":10000
			},
			{
				"id":20,
				"OperName":"格挡",
				"roleID":2,
				"skillid":32402,
				"skillType":1,
				"leafid":[],
				"mainkey":{ "key" : 2,"mode" : 3},
				"subkey":{ "key" : 1,"mode" : 1},
				"isboot":1,
				"sstate":1,
				"parmsecmin":0,
				"parmsecmax":10000
			},
			{
				"id":21,
				"OperName":"闪避",
				"roleID":2,
				"skillid":32401,
				"skillType":1,
				"leafid":[],
				"mainkey":{ "key" : 2,"mode" : 1},
				"subkey":{ "key" : 1,"mode" : 1},
				"isboot":1,
				"sstate":1,
				"parmsecmin":0,
				"parmsecmax":10000
			},
			{
				"id":22,
				"OperName":"受身",
				"roleID":2,
				"skillid":32404,
				"skillType":1,
				"leafid":[],
				"mainkey":{ "key" : 2,"mode" : 4},
				"subkey":{ "key" : 1,"mode" : 1},
				"isboot":1,
				"sstate":0,
				"parmsecmin":0,
				"parmsecmax":10000
			},
			{
				"id":23,
				"OperName":"空中冲刺",
				"roleID":2,
				"skillid":32403,
				"skillType":1,
				"leafid":[ 6, 17 ],
				"mainkey":{ "key" : 2,"mode" : 1},
				"subkey":{ "key" : 1,"mode" : 1},
				"isboot":1,
				"sstate":2,
				"parmsecmin":0,
				"parmsecmax":10000
			},
			{
				"id":24,
				"OperName":"跳跃",
				"roleID":2,
				"skillid":32301,
				"skillType":1,
				"leafid":[],
				"mainkey":{ "key" : 1,"mode" : 1},
				"subkey":{ "key" : 1,"mode" : 1},
				"isboot":1,
				"sstate":1,
				"parmsecmin":0,
				"parmsecmax":10000
			},
			{
				"id":25,
				"OperName":"2段跳跃",
				"roleID":2,
				"skillid":32302,
				"skillType":1,
				"leafid":[],
				"mainkey":{ "key" : 1,"mode" : 1},
				"subkey":{ "key" : 1,"mode" : 1},
				"isboot":1,
				"sstate":2,
				"parmsecmin":0,
				"parmsecmax":10000
			},
			{
				"id":26,
				"OperName":"技能1",
				"roleID":2,
				"skillid":22501,
				"skillType":0,
				"leafid":[],
				"mainkey":{ "key" : 5,"mode" : 1},
				"subkey":{ "key" : 1,"mode" : 1},
				"isboot":1,
				"sstate":1,
				"parmsecmin":0,
				"parmsecmax":10000
			},
			{
				"id":27,
				"OperName":"技能2",
				"roleID":2,
				"skillid":22601,
				"skillType":0,
				"leafid":[],
				"mainkey":{ "key" : 6,"mode" : 1},
				"subkey":{ "key" : 1,"mode" : 1},
				"isboot":1,
				"sstate":1,
				"parmsecmin":0,
				"parmsecmax":10000
			},
			{
				"id":28,
				"OperName":"技能3",
				"roleID":2,
				"skillid":22701,
				"skillType":0,
				"leafid":[],
				"mainkey":{ "key" : 7,"mode" : 1},
				"subkey":{ "key" : 1,"mode" : 1},
				"isboot":1,
				"sstate":1,
				"parmsecmin":0,
				"parmsecmax":10000
			},
			{
				"id":29,
				"OperName":"技能4",
				"roleID":2,
				"skillid":22801,
				"skillType":0,
				"leafid":[],
				"mainkey":{ "key" : 8,"mode" : 1},
				"subkey":{ "key" : 1,"mode" : 1},
				"isboot":1,
				"sstate":1,
				"parmsecmin":0,
				"parmsecmax":10000
			},
			{
				"id":1,
				"OperName":"地面1X",
				"roleID":3,
				"skillid":13101,
				"skillType":0,
				"leafid":[ 2, 18, 11, 20, 21 ],
				"mainkey":{ "key" : 3,"mode" : 1},
				"subkey":{ "key" : 1,"mode" : 1},
				"isboot":1,
				"sstate":1,
				"parmsecmin":1000,
				"parmsecmax":1000
			},
			{
				"id":2,
				"OperName":"地面2X",
				"roleID":3,
				"skillid":13102,
				"skillType":0,
				"leafid":[ 3, 18, 12, 20, 21 ],
				"mainkey":{ "key" : 3,"mode" : 1},
				"subkey":{ "key" : 1,"mode" : 1},
				"isboot":0,
				"sstate":1,
				"parmsecmin":0,
				"parmsecmax":10000
			},
			{
				"id":3,
				"OperName":"地面3X",
				"roleID":3,
				"skillid":13103,
				"skillType":0,
				"leafid":[ 4, 18, 13, 20, 21 ],
				"mainkey":{ "key" : 3,"mode" : 1},
				"subkey":{ "key" : 1,"mode" : 1},
				"isboot":0,
				"sstate":1,
				"parmsecmin":0,
				"parmsecmax":10000
			},
			{
				"id":4,
				"OperName":"地面4X",
				"roleID":3,
				"skillid":13104,
				"skillType":0,
				"leafid":[ 5, 18, 14, 20, 21 ],
				"mainkey":{ "key" : 3,"mode" : 1},
				"subkey":{ "key" : 1,"mode" : 1},
				"isboot":0,
				"sstate":1,
				"parmsecmin":0,
				"parmsecmax":10000
			},
			{
				"id":5,
				"OperName":"地面5X",
				"roleID":3,
				"skillid":13105,
				"skillType":0,
				"leafid":[ 15, 20, 21 ],
				"mainkey":{ "key" : 3,"mode" : 1},
				"subkey":{ "key" : 1,"mode" : 1},
				"isboot":0,
				"sstate":1,
				"parmsecmin":0,
				"parmsecmax":10000
			},
			{
				"id":6,
				"OperName":"空中1X",
				"roleID":3,
				"skillid":13106,
				"skillType":0,
				"leafid":[ 7, 19, 17, 22 ],
				"mainkey":{ "key" : 3,"mode" : 1},
				"subkey":{ "key" : 1,"mode" : 1},
				"isboot":1,
				"sstate":2,
				"parmsecmin":0,
				"parmsecmax":10000
			},
			{
				"id":7,
				"OperName":"空中2X",
				"roleID":3,
				"skillid":13107,
				"skillType":0,
				"leafid":[ 8, 19, 17, 22 ],
				"mainkey":{ "key" : 3,"mode" : 1},
				"subkey":{ "key" : 1,"mode" : 1},
				"isboot":0,
				"sstate":2,
				"parmsecmin":0,
				"parmsecmax":10000
			},
			{
				"id":8,
				"OperName":"空中3X",
				"roleID":3,
				"skillid":13108,
				"skillType":0,
				"leafid":[ 9, 19, 17, 22 ],
				"mainkey":{ "key" : 3,"mode" : 1},
				"subkey":{ "key" : 1,"mode" : 1},
				"isboot":0,
				"sstate":2,
				"parmsecmin":0,
				"parmsecmax":10000
			},
			{
				"id":9,
				"OperName":"空中4X",
				"roleID":3,
				"skillid":13109,
				"skillType":0,
				"leafid":[ 10, 19, 17, 22 ],
				"mainkey":{ "key" : 3,"mode" : 1},
				"subkey":{ "key" : 1,"mode" : 1},
				"isboot":0,
				"sstate":2,
				"parmsecmin":0,
				"parmsecmax":10000
			},
			{
				"id":10,
				"OperName":"空中5X",
				"roleID":3,
				"skillid":13110,
				"skillType":0,
				"leafid":[],
				"mainkey":{ "key" : 3,"mode" : 1},
				"subkey":{ "key" : 1,"mode" : 1},
				"isboot":0,
				"sstate":2,
				"parmsecmin":0,
				"parmsecmax":10000
			},
			{
				"id":11,
				"OperName":"Y连招1",
				"roleID":3,
				"skillid":13203,
				"skillType":0,
				"leafid":[],
				"mainkey":{ "key" : 4,"mode" : 1},
				"subkey":{ "key" : 1,"mode" : 1},
				"isboot":0,
				"sstate":1,
				"parmsecmin":0,
				"parmsecmax":10000
			},
			{
				"id":12,
				"OperName":"Y连招2",
				"roleID":3,
				"skillid":13204,
				"skillType":0,
				"leafid":[],
				"mainkey":{ "key" : 4,"mode" : 1},
				"subkey":{ "key" : 1,"mode" : 1},
				"isboot":0,
				"sstate":1,
				"parmsecmin":0,
				"parmsecmax":10000
			},
			{
				"id":13,
				"OperName":"Y连招3",
				"roleID":3,
				"skillid":13205,
				"skillType":0,
				"leafid":[],
				"mainkey":{ "key" : 4,"mode" : 1},
				"subkey":{ "key" : 1,"mode" : 1},
				"isboot":0,
				"sstate":1,
				"parmsecmin":0,
				"parmsecmax":10000
			},
			{
				"id":14,
				"OperName":"Y连招4",
				"roleID":3,
				"skillid":13206,
				"skillType":0,
				"leafid":[],
				"mainkey":{ "key" : 4,"mode" : 1},
				"subkey":{ "key" : 1,"mode" : 1},
				"isboot":0,
				"sstate":1,
				"parmsecmin":0,
				"parmsecmax":10000
			},
			{
				"id":15,
				"OperName":"Y连招5",
				"roleID":3,
				"skillid":13207,
				"skillType":0,
				"leafid":[],
				"mainkey":{ "key" : 4,"mode" : 1},
				"subkey":{ "key" : 1,"mode" : 1},
				"isboot":0,
				"sstate":1,
				"parmsecmin":0,
				"parmsecmax":10000
			},
			{
				"id":16,
				"OperName":"地面Y",
				"roleID":3,
				"skillid":13201,
				"skillType":0,
				"leafid":[],
				"mainkey":{ "key" : 4,"mode" : 1},
				"subkey":{ "key" : 1,"mode" : 1},
				"isboot":1,
				"sstate":1,
				"parmsecmin":0,
				"parmsecmax":10000
			},
			{
				"id":17,
				"OperName":"空中Y",
				"roleID":3,
				"skillid":13202,
				"skillType":0,
				"leafid":[],
				"mainkey":{ "key" : 4,"mode" : 1},
				"subkey":{ "key" : 1,"mode" : 1},
				"isboot":1,
				"sstate":2,
				"parmsecmin":0,
				"parmsecmax":10000
			},
			{
				"id":18,
				"OperName":"1段上挑",
				"roleID":3,
				"skillid":13301,
				"skillType":0,
				"leafid":[ 6, 17 ],
				"mainkey":{ "key" : 1,"mode" : 1},
				"subkey":{ "key" : 1,"mode" : 1},
				"isboot":0,
				"sstate":1,
				"parmsecmin":0,
				"parmsecmax":10000
			},
			{
				"id":19,
				"OperName":"2段上挑",
				"roleID":3,
				"skillid":13302,
				"skillType":0,
				"leafid":[ 6, 17 ],
				"mainkey":{ "key" : 1,"mode" : 1},
				"subkey":{ "key" : 1,"mode" : 1},
				"isboot":0,
				"sstate":2,
				"parmsecmin":0,
				"parmsecmax":10000
			},
			{
				"id":20,
				"OperName":"格挡",
				"roleID":3,
				"skillid":33402,
				"skillType":1,
				"leafid":[],
				"mainkey":{ "key" : 2,"mode" : 3},
				"subkey":{ "key" : 1,"mode" : 1},
				"isboot":1,
				"sstate":1,
				"parmsecmin":0,
				"parmsecmax":10000
			},
			{
				"id":21,
				"OperName":"闪避",
				"roleID":3,
				"skillid":33401,
				"skillType":1,
				"leafid":[],
				"mainkey":{ "key" : 2,"mode" : 1},
				"subkey":{ "key" : 1,"mode" : 1},
				"isboot":1,
				"sstate":1,
				"parmsecmin":0,
				"parmsecmax":10000
			},
			{
				"id":22,
				"OperName":"受身",
				"roleID":3,
				"skillid":33404,
				"skillType":1,
				"leafid":[],
				"mainkey":{ "key" : 2,"mode" : 4},
				"subkey":{ "key" : 1,"mode" : 1},
				"isboot":1,
				"sstate":0,
				"parmsecmin":0,
				"parmsecmax":10000
			},
			{
				"id":23,
				"OperName":"空中冲刺",
				"roleID":3,
				"skillid":33403,
				"skillType":1,
				"leafid":[ 6, 17 ],
				"mainkey":{ "key" : 2,"mode" : 1},
				"subkey":{ "key" : 1,"mode" : 1},
				"isboot":1,
				"sstate":2,
				"parmsecmin":0,
				"parmsecmax":10000
			},
			{
				"id":24,
				"OperName":"跳跃",
				"roleID":3,
				"skillid":33301,
				"skillType":1,
				"leafid":[],
				"mainkey":{ "key" : 1,"mode" : 1},
				"subkey":{ "key" : 1,"mode" : 1},
				"isboot":1,
				"sstate":1,
				"parmsecmin":0,
				"parmsecmax":10000
			},
			{
				"id":25,
				"OperName":"2段跳跃",
				"roleID":3,
				"skillid":33302,
				"skillType":1,
				"leafid":[],
				"mainkey":{ "key" : 1,"mode" : 1},
				"subkey":{ "key" : 1,"mode" : 1},
				"isboot":1,
				"sstate":2,
				"parmsecmin":0,
				"parmsecmax":10000
			},
			{
				"id":26,
				"OperName":"技能1",
				"roleID":3,
				"skillid":23501,
				"skillType":0,
				"leafid":[],
				"mainkey":{ "key" : 5,"mode" : 1},
				"subkey":{ "key" : 1,"mode" : 1},
				"isboot":1,
				"sstate":1,
				"parmsecmin":0,
				"parmsecmax":10000
			},
			{
				"id":27,
				"OperName":"技能2",
				"roleID":3,
				"skillid":23601,
				"skillType":0,
				"leafid":[],
				"mainkey":{ "key" : 6,"mode" : 1},
				"subkey":{ "key" : 1,"mode" : 1},
				"isboot":1,
				"sstate":1,
				"parmsecmin":0,
				"parmsecmax":10000
			},
			{
				"id":28,
				"OperName":"技能3",
				"roleID":3,
				"skillid":23701,
				"skillType":0,
				"leafid":[],
				"mainkey":{ "key" : 7,"mode" : 1},
				"subkey":{ "key" : 1,"mode" : 1},
				"isboot":1,
				"sstate":1,
				"parmsecmin":0,
				"parmsecmax":10000
			},
			{
				"id":29,
				"OperName":"技能4",
				"roleID":3,
				"skillid":23801,
				"skillType":0,
				"leafid":[],
				"mainkey":{ "key" : 8,"mode" : 1},
				"subkey":{ "key" : 1,"mode" : 1},
				"isboot":1,
				"sstate":1,
				"parmsecmin":0,
				"parmsecmax":10000
			}
		]

}
